chiaro/__init__.py
chiaro/_version.py
chiaro/core/__init__.py
chiaro/core/base.py
chiaro/core/chart.py
chiaro/core/io.py
chiaro/core/types.py
chiaro/express/__init__.py
chiaro/express/api.py
chiaro/geoms/__init__.py
chiaro/geoms/bar.py
chiaro/geoms/line.py
chiaro/geoms/point.py
chiaro/guides/__init__.py
chiaro/guides/colorbar.py
chiaro/guides/legend.py
chiaro/scales/__init__.py
chiaro/scales/continuous.py
chiaro/scales/discrete.py
chiaro-0.1.2.dist-info/METADATA
chiaro-0.1.2.dist-info/WHEEL
chiaro-0.1.2.dist-info/licenses/LICENSE
chiaro-0.1.2.dist-info/RECORD
