Metadata-Version: 2.4
Name: chiaro
Version: 0.1.2
Summary: Fluent Grammar-of-Graphics in Python
Project-URL: Homepage, https://github.com/rabeez/chiaro
License: Copyright 2025 Rabeez Riaz
License-File: LICENSE
Requires-Python: >=3.11
Requires-Dist: bokeh
Requires-Dist: narwhals
